{"title":"PixAndVideo - Sophie Moone","uid":6653363,"size":803370796,"categoryP":"porn","categoryS":"movies","magnet":"?xt=urn:btih:05c08f0262782728ae58a2cab00440cf6fa17a75&amp;dn=PixAndVideo+-+Sophie+Moone&amp;tr=udp%3A%2F%2Ftracker.openbittorrent.com%3A80&amp;tr=udp%3A%2F%2Fopen.demonii.com%3A1337&amp;tr=udp%3A%2F%2Ftracker.coppersurfer.tk%3A6969&amp;tr=udp%3A%2F%2Fexodus.desync.com%3A6969","seeders":0,"leechers":1,"uploader":"exmnova","files":1,"time":1315238675,"description":"PixAndVideo - Sophie Moone\n &lt;a href=&quot;\nhttp://0.picswan.com/show.php/16624_2.jpg.html&quot; rel=&quot;nofollow&quot; target=&quot;_NEW&quot;&gt;\nhttp://0.picswan.com/show.php/16624_2.jpg.html&lt;/a&gt;\n &lt;a href=&quot;\nhttp://0.picswan.com/show.php/16623_1.jpg.html&quot; rel=&quot;nofollow&quot; target=&quot;_NEW&quot;&gt;\nhttp://0.picswan.com/show.php/16623_1.jpg.html&lt;/a&gt;\n","torrent":{"xt":"urn:btih:05c08f0262782728ae58a2cab00440cf6fa17a75","amp;dn":"PixAndVideo+-+Sophie+Moone","amp;tr":["udp%3A%2F%2Ftracker.openbittorrent.com%3A80","udp%3A%2F%2Fopen.demonii.com%3A1337","udp%3A%2F%2Ftracker.coppersurfer.tk%3A6969","udp%3A%2F%2Fexodus.desync.com%3A6969"],"infoHash":"05c08f0262782728ae58a2cab00440cf6fa17a75","infoHashBuffer":{"type":"Buffer","data":[5,192,143,2,98,120,39,40,174,88,162,202,176,4,64,207,111,161,122,117]},"announce":[],"urlList":[]}}