{"title":"ATK Hairy Lena 015IGR - 10 Sets","uid":6526497,"size":213328299,"categoryP":"porn","categoryS":"pictures","magnet":"?xt=urn:btih:05fd597ad5923a51714a9d0a836c19060d6b73cc&amp;dn=ATK+Hairy+Lena+015IGR+-+10+Sets&amp;tr=udp%3A%2F%2Ftracker.openbittorrent.com%3A80&amp;tr=udp%3A%2F%2Fopen.demonii.com%3A1337&amp;tr=udp%3A%2F%2Ftracker.coppersurfer.tk%3A6969&amp;tr=udp%3A%2F%2Fexodus.desync.com%3A6969","seeders":0,"leechers":1,"uploader":"thegreenfrog","files":-1,"time":1310179979,"description":"Pretty sure she is new. ","torrent":{"xt":"urn:btih:05fd597ad5923a51714a9d0a836c19060d6b73cc","amp;dn":"ATK+Hairy+Lena+015IGR+-+10+Sets","amp;tr":["udp%3A%2F%2Ftracker.openbittorrent.com%3A80","udp%3A%2F%2Fopen.demonii.com%3A1337","udp%3A%2F%2Ftracker.coppersurfer.tk%3A6969","udp%3A%2F%2Fexodus.desync.com%3A6969"],"infoHash":"05fd597ad5923a51714a9d0a836c19060d6b73cc","infoHashBuffer":{"type":"Buffer","data":[5,253,89,122,213,146,58,81,113,74,157,10,131,108,25,6,13,107,115,204]},"announce":[],"urlList":[]}}