{"title":"Cowboy.Builders.S05E01.WS.PDTV.XviD-BARGE","uid":6523902,"size":372993004,"categoryP":"video","categoryS":"tv_shows","magnet":"?xt=urn:btih:09135c38435285bea43e88d0edbf268d21e87cfd&amp;dn=Cowboy.Builders.S05E01.WS.PDTV.XviD-BARGE&amp;tr=udp%3A%2F%2Ftracker.openbittorrent.com%3A80&amp;tr=udp%3A%2F%2Fopen.demonii.com%3A1337&amp;tr=udp%3A%2F%2Ftracker.coppersurfer.tk%3A6969&amp;tr=udp%3A%2F%2Fexodus.desync.com%3A6969","seeders":0,"leechers":1,"uploader":"torrentzone","files":28,"time":1310093394,"description":"Torrent Uploaded By https://torrentzone.net \n \n\nNOTE this sever does not have the power to extract effecently but i enoy sharing so i still upload \n\n\nLike this torrent? Come Join us at https://torrentzone.net/ For faster downloads, no fakes and NO RARS.\n\n\n We are Building a great community with many torrents AND FASTER DOWNLOADS. Uploads are fast and great quality!","torrent":{"xt":"urn:btih:09135c38435285bea43e88d0edbf268d21e87cfd","amp;dn":"Cowboy.Builders.S05E01.WS.PDTV.XviD-BARGE","amp;tr":["udp%3A%2F%2Ftracker.openbittorrent.com%3A80","udp%3A%2F%2Fopen.demonii.com%3A1337","udp%3A%2F%2Ftracker.coppersurfer.tk%3A6969","udp%3A%2F%2Fexodus.desync.com%3A6969"],"infoHash":"09135c38435285bea43e88d0edbf268d21e87cfd","infoHashBuffer":{"type":"Buffer","data":[9,19,92,56,67,82,133,190,164,62,136,208,237,191,38,141,33,232,124,253]},"announce":[],"urlList":[]}}