{"title":"Fast.Five.2011.NTSC.DVDR-FiCODVDR READ DESCRIPTION!!!!","uid":6658091,"size":4759498046,"categoryP":"video","categoryS":"movies_dvdr","magnet":"?xt=urn:btih:0ccd02e652f95002d0347b6967333009f61ca463&amp;dn=Fast.Five.2011.NTSC.DVDR-FiCODVDR+READ+DESCRIPTION%21%21%21%21&amp;tr=udp%3A%2F%2Ftracker.openbittorrent.com%3A80&amp;tr=udp%3A%2F%2Fopen.demonii.com%3A1337&amp;tr=udp%3A%2F%2Ftracker.coppersurfer.tk%3A6969&amp;tr=udp%3A%2F%2Fexodus.desync.com%3A6969","seeders":0,"leechers":0,"uploader":"Jon.Pson","files":-1,"time":1315356492,"description":"EDIT::::::::\nDue to the disabling of Editing and Deletion of torrents I have to re-upload this Fast.Five.2011.NTSC.DVDR-FiCODVDR torrent. I found an .!ut file in the hashed Sample folder which made the torrent appear without seeders. \n\nIf you are downloading this torrent: http://thepiratebay.se/torrent/6657697/Fast.Five.2011.NTSC.DVDR-FiCODVDR, then delete it and download this instead. Sorry about this.\n\nEDIT END::::::::\n\n \nThis DVD-R is erroneous on some torrent sites. That's why I have decided to upload it here. For those who get the file ficodvdr-ffs.r28-MISSING, download this torrent and chose Skip Hash Control. \n\nTHIS IS NOT MY DVD-R RELEASE. I ONLY UPLOAD IT FOR OTHERS TO REPAIR AN ERROR!!!!!!\n\n-----------------------------------------------------------------------------------\nORIGINAL DESCRIPTION OF THE TORRENT:\n\nP.R.O.U.D.L.Y P.R.E.S.E.N.T.S\n\nFast.Five.2011.NTSC.DVDR-FiCODVDR\n\nRELEASE DATE..&gt; 5/9/2011 &lt; SUPPLIER.......&gt; FiCO CREW &lt;\nSTREET DATE...&gt; &lt; CRACKER/RIPPER.&gt; FiCO CREW &lt;\nRELEASE TYPE..&gt; &lt; ENCODER........&gt; &lt;\nRATING [iMDb].&gt; 7.5 (60K+) &lt; THEATRE DATE...&gt; &lt;\n&lt; GENRE..........&gt; Action,etc &lt;\nRUNTIME.......&gt; &lt; DISKS..........&gt; &lt;\n&lt; MOVIE SIZE.....&gt; 4.35 GB &lt;\nVIDEO FORMAT..&gt; R4 &lt;\n\nRELEASE NOTES\n\nAUDiO SUBTiTLES, English 2.0 AC3, ENGLiSH, Spanish 5.1 AC3, SPANiSH, Portugal 5.1 AC3, Portugal\nASPECT RATiO, 2.35:1\n\nViDEO, Untouched, CCE\n\nMENU, Untouched\n\nDVD EXTRAS, All included\nPasses\nBitrate\n  &lt;a href=&quot;\nhttp://www.imdb.com/title/tt1596343/&quot; rel=&quot;nofollow&quot; target=&quot;_NEW&quot;&gt;\nhttp://www.imdb.com/title/tt1596343/&lt;/a&gt;\nDirected by: Justin Lin\n\nVin Diesel ... Dominic Toretto\nPaul Walker ... Brian O'Conner\nJordana Brewster ... Mia Toretto\nTyrese Gibson ... Roman Pearce\nLudacris ... Tej Parker\n\nDominic and his crew find themselves on the wrong side of the law once\nagain as they try to switch lanes between a ruthless drug lord and a\nrelentless federal agent","torrent":{"xt":"urn:btih:0ccd02e652f95002d0347b6967333009f61ca463","amp;dn":"Fast.Five.2011.NTSC.DVDR-FiCODVDR+READ+DESCRIPTION%21%21%21%21","amp;tr":["udp%3A%2F%2Ftracker.openbittorrent.com%3A80","udp%3A%2F%2Fopen.demonii.com%3A1337","udp%3A%2F%2Ftracker.coppersurfer.tk%3A6969","udp%3A%2F%2Fexodus.desync.com%3A6969"],"infoHash":"0ccd02e652f95002d0347b6967333009f61ca463","infoHashBuffer":{"type":"Buffer","data":[12,205,2,230,82,249,80,2,208,52,123,105,103,51,48,9,246,28,164,99]},"announce":[],"urlList":[]}}