{"title":"Playboy-usa Agosto 2011","uid":6648478,"size":69956777,"categoryP":"porn","categoryS":"other","magnet":"?xt=urn:btih:0e1db72048b1445899965af272e2fceb81902c26&amp;dn=Playboy-usa+Agosto+2011&amp;tr=udp%3A%2F%2Ftracker.openbittorrent.com%3A80&amp;tr=udp%3A%2F%2Fopen.demonii.com%3A1337&amp;tr=udp%3A%2F%2Ftracker.coppersurfer.tk%3A6969&amp;tr=udp%3A%2F%2Fexodus.desync.com%3A6969","seeders":0,"leechers":0,"uploader":"furtaperas","files":-1,"time":1315040765,"description":"playboy","torrent":{"xt":"urn:btih:0e1db72048b1445899965af272e2fceb81902c26","amp;dn":"Playboy-usa+Agosto+2011","amp;tr":["udp%3A%2F%2Ftracker.openbittorrent.com%3A80","udp%3A%2F%2Fopen.demonii.com%3A1337","udp%3A%2F%2Ftracker.coppersurfer.tk%3A6969","udp%3A%2F%2Fexodus.desync.com%3A6969"],"infoHash":"0e1db72048b1445899965af272e2fceb81902c26","infoHashBuffer":{"type":"Buffer","data":[14,29,183,32,72,177,68,88,153,150,90,242,114,226,252,235,129,144,44,38]},"announce":[],"urlList":[]}}