{"title":"Taking Woodstock 2009 DVDRip.h264.AC3-rickity","uid":6570798,"size":1321097659,"categoryP":"video","categoryS":"movies","magnet":"?xt=urn:btih:1eccec03bb07bcfca2fb914e64520f5aab21b3c5&amp;dn=Taking+Woodstock+2009+DVDRip.h264.AC3-rickity&amp;tr=udp%3A%2F%2Ftracker.openbittorrent.com%3A80&amp;tr=udp%3A%2F%2Fopen.demonii.com%3A1337&amp;tr=udp%3A%2F%2Ftracker.coppersurfer.tk%3A6969&amp;tr=udp%3A%2F%2Fexodus.desync.com%3A6969","seeders":0,"leechers":1,"uploader":"rickity","files":-1,"time":1311963579,"description":"A man working at his parents' motel in the Catskills inadvertently sets in motion the generation-defining concert in the summer of 1969.","torrent":{"xt":"urn:btih:1eccec03bb07bcfca2fb914e64520f5aab21b3c5","amp;dn":"Taking+Woodstock+2009+DVDRip.h264.AC3-rickity","amp;tr":["udp%3A%2F%2Ftracker.openbittorrent.com%3A80","udp%3A%2F%2Fopen.demonii.com%3A1337","udp%3A%2F%2Ftracker.coppersurfer.tk%3A6969","udp%3A%2F%2Fexodus.desync.com%3A6969"],"infoHash":"1eccec03bb07bcfca2fb914e64520f5aab21b3c5","infoHashBuffer":{"type":"Buffer","data":[30,204,236,3,187,7,188,252,162,251,145,78,100,82,15,90,171,33,179,197]},"announce":[],"urlList":[]}}