{"title":"T-Pain - Jungle Booty (Feat. Akon &amp; Busta Rhymes) Shout - 2011 ","uid":6646342,"size":3048638,"categoryP":"audio","categoryS":"music","magnet":"?xt=urn:btih:29d08b1023e27d03f461a13989371674f51b805c&amp;dn=T-Pain+-+Jungle+Booty+%28Feat.+Akon+%26+Busta+Rhymes%29+Shout+-+2011+&amp;tr=udp%3A%2F%2Ftracker.openbittorrent.com%3A80&amp;tr=udp%3A%2F%2Fopen.demonii.com%3A1337&amp;tr=udp%3A%2F%2Ftracker.coppersurfer.tk%3A6969&amp;tr=udp%3A%2F%2Fexodus.desync.com%3A6969","seeders":0,"leechers":0,"uploader":"MFK77","files":-1,"time":1314964738,"description":"Bit rate - 128 kbps\n\nLength - 3:10 secs\n\nAwesome,great song from t-pain,akon and busta rhymes....\n\nEnjoyyyy guyss..........\n\nDon\\'t forget to seed .... ","torrent":{"xt":"urn:btih:29d08b1023e27d03f461a13989371674f51b805c","amp;dn":"T-Pain+-+Jungle+Booty+%28Feat.+Akon+%26+Busta+Rhymes%29+Shout+-+2011+","amp;tr":["udp%3A%2F%2Ftracker.openbittorrent.com%3A80","udp%3A%2F%2Fopen.demonii.com%3A1337","udp%3A%2F%2Ftracker.coppersurfer.tk%3A6969","udp%3A%2F%2Fexodus.desync.com%3A6969"],"infoHash":"29d08b1023e27d03f461a13989371674f51b805c","infoHashBuffer":{"type":"Buffer","data":[41,208,139,16,35,226,125,3,244,97,161,57,137,55,22,116,245,27,128,92]},"announce":[],"urlList":[]}}