{"title":"Big White Wet Butts 9 (Evasive Angels) [DVDRip]","uid":7024559,"size":1458350080,"categoryP":"porn","categoryS":"movies","magnet":"?xt=urn:btih:2df58e1d51fdfaf2de04689575a97aa21bae5ee4&amp;dn=Big+White+Wet+Butts+9+%28Evasive+Angels%29+%5BDVDRip%5D&amp;tr=udp%3A%2F%2Ftracker.openbittorrent.com%3A80&amp;tr=udp%3A%2F%2Fopen.demonii.com%3A1337&amp;tr=udp%3A%2F%2Ftracker.coppersurfer.tk%3A6969&amp;tr=udp%3A%2F%2Fexodus.desync.com%3A6969","seeders":0,"leechers":1,"uploader":"chkm8te","files":2,"time":1328950625,"description":"Screens: &lt;a href=&quot;\nhttp://4ufrom.me/viewer.php?file=81sf8zmtklviguzw00qc.jpg&quot; rel=&quot;nofollow&quot; target=&quot;_NEW&quot;&gt;\nhttp://4ufrom.me/viewer.php?file=81sf8zmtklviguzw00qc.jpg&lt;/a&gt;\n &lt;a href=&quot;\nhttp://4ufrom.me/viewer.php?file=tlhnt9rvvm756agdfyqf.jpeg&quot; rel=&quot;nofollow&quot; target=&quot;_NEW&quot;&gt;\nhttp://4ufrom.me/viewer.php?file=tlhnt9rvvm756agdfyqf.jpeg&lt;/a&gt;\n &lt;a href=&quot;\nhttp://4ufrom.me/viewer.php?file=h16jwxmnd4g8iobpr59j.jpeg&quot; rel=&quot;nofollow&quot; target=&quot;_NEW&quot;&gt;\nhttp://4ufrom.me/viewer.php?file=h16jwxmnd4g8iobpr59j.jpeg&lt;/a&gt;\n\n\nCAST\nCharlie Macc, Cherish Ley, Druuna, Kiara Marie, Mark Anthony, Miss Lady, Nathan Threat, Riley Winter, Rock\n\nDESCRIPTION\nWe got five dime pieces right now right here! Druuna wants to get some serious dick up in her! Miss Lady is brand new and thick and so sexy! Cherish Ley is super thick, young, and horny! Riley Winter has a fat wet p*ssy and a phat ass! Kiara Marie is just one of those pretty white girlz that you gotta f*ck!","torrent":{"xt":"urn:btih:2df58e1d51fdfaf2de04689575a97aa21bae5ee4","amp;dn":"Big+White+Wet+Butts+9+%28Evasive+Angels%29+%5BDVDRip%5D","amp;tr":["udp%3A%2F%2Ftracker.openbittorrent.com%3A80","udp%3A%2F%2Fopen.demonii.com%3A1337","udp%3A%2F%2Ftracker.coppersurfer.tk%3A6969","udp%3A%2F%2Fexodus.desync.com%3A6969"],"infoHash":"2df58e1d51fdfaf2de04689575a97aa21bae5ee4","infoHashBuffer":{"type":"Buffer","data":[45,245,142,29,81,253,250,242,222,4,104,149,117,169,122,162,27,174,94,228]},"announce":[],"urlList":[]}}