{"title":"Stoya Web - Whore ~ Stoya ~ 22.7.11","uid":6562088,"size":1467815936,"categoryP":"porn","categoryS":"movies","magnet":"?xt=urn:btih:3a9867da483f3d5c8740cc562cb6c56e3eb36b2b&amp;dn=Stoya+Web+-+Whore+%7E+Stoya+%7E+22.7.11&amp;tr=udp%3A%2F%2Ftracker.openbittorrent.com%3A80&amp;tr=udp%3A%2F%2Fopen.demonii.com%3A1337&amp;tr=udp%3A%2F%2Ftracker.coppersurfer.tk%3A6969&amp;tr=udp%3A%2F%2Fexodus.desync.com%3A6969","seeders":0,"leechers":1,"uploader":"brego45","files":2,"time":1311525384,"description":"Covers\n------------     \n\n &lt;a href=&quot;\nhttp://desibbrg.net/imghost/show.php?img=408347_Stoyaweb1.jpg.html&quot; rel=&quot;nofollow&quot; target=&quot;_NEW&quot;&gt;\nhttp://desibbrg.net/imghost/show.php?img=408347_Stoyaweb1.jpg.html&lt;/a&gt;\n\n\n &lt;a href=&quot;\nhttp://desibbrg.net/imghost/show.php?img=408346_Stoyaweb2.jpg.html&quot; rel=&quot;nofollow&quot; target=&quot;_NEW&quot;&gt;\nhttp://desibbrg.net/imghost/show.php?img=408346_Stoyaweb2.jpg.html&lt;/a&gt;\n\n\nScreenshots\n-----------------  \n   \n &lt;a href=&quot;\nhttp://desibbrg.net/imghost/show.php?img=408349_StoyaWebW.horeStoyaCD1.AVIthumbs2011.07.2416.26.15.jpg.html&quot; rel=&quot;nofollow&quot; target=&quot;_NEW&quot;&gt;\nhttp://desibbrg.net/imghost/show.php?img=408349_StoyaWebW.horeStoyaCD1.AVIthumbs2011.07.2416.26.15.jpg.html&lt;/a&gt;\n\n\n &lt;a href=&quot;\nhttp://desibbrg.net/imghost/show.php?img=408348_StoyaWebW.horeStoyacd2.avithumbs2011.07.2416.30.19.jpg.html&quot; rel=&quot;nofollow&quot; target=&quot;_NEW&quot;&gt;\nhttp://desibbrg.net/imghost/show.php?img=408348_StoyaWebW.horeStoyacd2.avithumbs2011.07.2416.30.19.jpg.html&lt;/a&gt;\n\n\n\nCheck out my other 3000+ torrent releases\n\n\n----------------------------------------------     \n\n &lt;a href=&quot;\nhttp://thepiratebay.se/user/brego45&quot; rel=&quot;nofollow&quot; target=&quot;_NEW&quot;&gt;\nhttp://thepiratebay.se/user/brego45&lt;/a&gt;","torrent":{"xt":"urn:btih:3a9867da483f3d5c8740cc562cb6c56e3eb36b2b","amp;dn":"Stoya+Web+-+Whore+%7E+Stoya+%7E+22.7.11","amp;tr":["udp%3A%2F%2Ftracker.openbittorrent.com%3A80","udp%3A%2F%2Fopen.demonii.com%3A1337","udp%3A%2F%2Ftracker.coppersurfer.tk%3A6969","udp%3A%2F%2Fexodus.desync.com%3A6969"],"infoHash":"3a9867da483f3d5c8740cc562cb6c56e3eb36b2b","infoHashBuffer":{"type":"Buffer","data":[58,152,103,218,72,63,61,92,135,64,204,86,44,182,197,110,62,179,107,43]},"announce":[],"urlList":[]}}