{"title":"Anita 18andbusty.rar","uid":6523340,"size":2163651,"categoryP":"porn","categoryS":"pictures","magnet":"?xt=urn:btih:3cb48f4c9111c95a0460b8e4e04692100c0fdd19&amp;dn=Anita+18andbusty.rar&amp;tr=udp%3A%2F%2Ftracker.openbittorrent.com%3A80&amp;tr=udp%3A%2F%2Fopen.demonii.com%3A1337&amp;tr=udp%3A%2F%2Ftracker.coppersurfer.tk%3A6969&amp;tr=udp%3A%2F%2Fexodus.desync.com%3A6969","seeders":0,"leechers":1,"uploader":"dodgerblue","files":1,"time":1310072354,"description":" &lt;a href=&quot;http://imgchili.com/show/29/29652_3.jpg&quot; rel=&quot;nofollow&quot; target=&quot;_NEW&quot;&gt;http://imgchili.com/show/29/29652_3.jpg&lt;/a&gt; &lt;a href=&quot;\nhttp://imgchili.com/show/29/29653_5.jpg&quot; rel=&quot;nofollow&quot; target=&quot;_NEW&quot;&gt;\nhttp://imgchili.com/show/29/29653_5.jpg&lt;/a&gt; &lt;a href=&quot;\nhttp://imgchili.com/show/29/29654_8.jpg&quot; rel=&quot;nofollow&quot; target=&quot;_NEW&quot;&gt;\nhttp://imgchili.com/show/29/29654_8.jpg&lt;/a&gt; &lt;a href=&quot;\nhttp://imgchili.com/show/29/29655_9.jpg&quot; rel=&quot;nofollow&quot; target=&quot;_NEW&quot;&gt;\nhttp://imgchili.com/show/29/29655_9.jpg&lt;/a&gt; &lt;a href=&quot;\nhttp://imgchili.com/show/29/29656_14.jpg&quot; rel=&quot;nofollow&quot; target=&quot;_NEW&quot;&gt;\nhttp://imgchili.com/show/29/29656_14.jpg&lt;/a&gt; &lt;a href=&quot;\nhttp://imgchili.com/show/29/29657_19.jpg&quot; rel=&quot;nofollow&quot; target=&quot;_NEW&quot;&gt;\nhttp://imgchili.com/show/29/29657_19.jpg&lt;/a&gt; &lt;a href=&quot;\nhttp://imgchili.com/show/29/29658_22.jpg&quot; rel=&quot;nofollow&quot; target=&quot;_NEW&quot;&gt;\nhttp://imgchili.com/show/29/29658_22.jpg&lt;/a&gt; &lt;a href=&quot;\nhttp://imgchili.com/show/29/29659_2.jpg&quot; rel=&quot;nofollow&quot; target=&quot;_NEW&quot;&gt;\nhttp://imgchili.com/show/29/29659_2.jpg&lt;/a&gt; &lt;a href=&quot;\nhttp://imgchili.com/show/29/29660_3.jpg&quot; rel=&quot;nofollow&quot; target=&quot;_NEW&quot;&gt;\nhttp://imgchili.com/show/29/29660_3.jpg&lt;/a&gt; &lt;a href=&quot;\nhttp://imgchili.com/show/29/29661_7.jpg&quot; rel=&quot;nofollow&quot; target=&quot;_NEW&quot;&gt;\nhttp://imgchili.com/show/29/29661_7.jpg&lt;/a&gt; &lt;a href=&quot;\nhttp://imgchili.com/show/29/29662_10.jpg&quot; rel=&quot;nofollow&quot; target=&quot;_NEW&quot;&gt;\nhttp://imgchili.com/show/29/29662_10.jpg&lt;/a&gt; &lt;a href=&quot;\nhttp://imgchili.com/show/29/29663_15.jpg&quot; rel=&quot;nofollow&quot; target=&quot;_NEW&quot;&gt;\nhttp://imgchili.com/show/29/29663_15.jpg&lt;/a&gt;","torrent":{"xt":"urn:btih:3cb48f4c9111c95a0460b8e4e04692100c0fdd19","amp;dn":"Anita+18andbusty.rar","amp;tr":["udp%3A%2F%2Ftracker.openbittorrent.com%3A80","udp%3A%2F%2Fopen.demonii.com%3A1337","udp%3A%2F%2Ftracker.coppersurfer.tk%3A6969","udp%3A%2F%2Fexodus.desync.com%3A6969"],"infoHash":"3cb48f4c9111c95a0460b8e4e04692100c0fdd19","infoHashBuffer":{"type":"Buffer","data":[60,180,143,76,145,17,201,90,4,96,184,228,224,70,146,16,12,15,221,25]},"announce":[],"urlList":[]}}