{"title":"VA - Fuse 04 [1998][Tech-House]","uid":6529819,"size":166801863,"categoryP":"audio","categoryS":"music","magnet":"?xt=urn:btih:4b0437037fca23ddf59c8b34bdb93b1647d74032&amp;dn=VA+-+Fuse+04+%5B1998%5D%5BTech-House%5D&amp;tr=udp%3A%2F%2Ftracker.openbittorrent.com%3A80&amp;tr=udp%3A%2F%2Fopen.demonii.com%3A1337&amp;tr=udp%3A%2F%2Ftracker.coppersurfer.tk%3A6969&amp;tr=udp%3A%2F%2Fexodus.desync.com%3A6969","seeders":0,"leechers":1,"uploader":null,"files":3,"time":1310256248,"description":" &lt;a href=&quot;http://www.discogs.com/Various-Fuse-04-One-Thousand-And-One-Night/release/78796&quot; rel=&quot;nofollow&quot; target=&quot;_NEW&quot;&gt;http://www.discogs.com/Various-Fuse-04-One-Thousand-And-One-Night/release/78796&lt;/a&gt;\n\nEncoded at 320kbps. Cue sheet included","torrent":{"xt":"urn:btih:4b0437037fca23ddf59c8b34bdb93b1647d74032","amp;dn":"VA+-+Fuse+04+%5B1998%5D%5BTech-House%5D","amp;tr":["udp%3A%2F%2Ftracker.openbittorrent.com%3A80","udp%3A%2F%2Fopen.demonii.com%3A1337","udp%3A%2F%2Ftracker.coppersurfer.tk%3A6969","udp%3A%2F%2Fexodus.desync.com%3A6969"],"infoHash":"4b0437037fca23ddf59c8b34bdb93b1647d74032","infoHashBuffer":{"type":"Buffer","data":[75,4,55,3,127,202,35,221,245,156,139,52,189,185,59,22,71,215,64,50]},"announce":[],"urlList":[]}}