{"title":"TsSeduction------13376 - Jessica Host  TS Foxxy and Parker Lon","uid":6512542,"size":603555868,"categoryP":"porn","categoryS":"movies","magnet":"?xt=urn:btih:4c44251f173c4344cdfe46e028eb59f99643896d&amp;dn=TsSeduction------13376+-+Jessica+Host++TS+Foxxy+and+Parker+Lon&amp;tr=udp%3A%2F%2Ftracker.openbittorrent.com%3A80&amp;tr=udp%3A%2F%2Fopen.demonii.com%3A1337&amp;tr=udp%3A%2F%2Ftracker.coppersurfer.tk%3A6969&amp;tr=udp%3A%2F%2Fexodus.desync.com%3A6969","seeders":0,"leechers":1,"uploader":"merzedes","files":185,"time":1309694002,"description":"From Kink.com    (Ts Seduction)   +  Pics\n\n\n\nFoxxy and her boyfriend convince Jessica Host to join them for a night of all kinds of fucking. Parker hits the jack pot of cock in this update as the two women work him over with their hard dicks. \nThe gagging blow jobs, leads to deep ass fucking and pure punishment for Parker who is now the fuck toy. Jessica demands that he fuck Foxxy while she smothers Foxxy with her luscious tits and each girl gets their cock ready to pop by rubbing them together in Parker's open, wet mouth. This is the ultimate fuck fest.\n\n\n\nScreens &lt;a href=&quot; http://www.tsseduction.com/site/shoot.jsp?shootId=13376&quot; rel=&quot;nofollow&quot; target=&quot;_NEW&quot;&gt; http://www.tsseduction.com/site/shoot.jsp?shootId=13376&lt;/a&gt;\n\n\n\nCheerz  :-)","torrent":{"xt":"urn:btih:4c44251f173c4344cdfe46e028eb59f99643896d","amp;dn":"TsSeduction------13376+-+Jessica+Host++TS+Foxxy+and+Parker+Lon","amp;tr":["udp%3A%2F%2Ftracker.openbittorrent.com%3A80","udp%3A%2F%2Fopen.demonii.com%3A1337","udp%3A%2F%2Ftracker.coppersurfer.tk%3A6969","udp%3A%2F%2Fexodus.desync.com%3A6969"],"infoHash":"4c44251f173c4344cdfe46e028eb59f99643896d","infoHashBuffer":{"type":"Buffer","data":[76,68,37,31,23,60,67,68,205,254,70,224,40,235,89,249,150,67,137,109]},"announce":[],"urlList":[]}}