{"title":"[BrokeAmateurs.com] Salena (Blowjob Interview)","uid":6867570,"size":270925669,"categoryP":"porn","categoryS":"movie_clips","magnet":"?xt=urn:btih:4d6c5659fd225c3648433dd7b9983572ee285dc4&amp;dn=%5BBrokeAmateurs.com%5D+Salena+%28Blowjob+Interview%29&amp;tr=udp%3A%2F%2Ftracker.openbittorrent.com%3A80&amp;tr=udp%3A%2F%2Fopen.demonii.com%3A1337&amp;tr=udp%3A%2F%2Ftracker.coppersurfer.tk%3A6969&amp;tr=udp%3A%2F%2Fexodus.desync.com%3A6969","seeders":0,"leechers":1,"uploader":"chkm8te","files":1,"time":1323164270,"description":"Screens: &lt;a href=&quot;\nhttp://4ufrom.me/viewer.php?file=hkajhimfwiwiu9tcfzud.jpg&quot; rel=&quot;nofollow&quot; target=&quot;_NEW&quot;&gt;\nhttp://4ufrom.me/viewer.php?file=hkajhimfwiwiu9tcfzud.jpg&lt;/a&gt;","torrent":{"xt":"urn:btih:4d6c5659fd225c3648433dd7b9983572ee285dc4","amp;dn":"%5BBrokeAmateurs.com%5D+Salena+%28Blowjob+Interview%29","amp;tr":["udp%3A%2F%2Ftracker.openbittorrent.com%3A80","udp%3A%2F%2Fopen.demonii.com%3A1337","udp%3A%2F%2Ftracker.coppersurfer.tk%3A6969","udp%3A%2F%2Fexodus.desync.com%3A6969"],"infoHash":"4d6c5659fd225c3648433dd7b9983572ee285dc4","infoHashBuffer":{"type":"Buffer","data":[77,108,86,89,253,34,92,54,72,67,61,215,185,152,53,114,238,40,93,196]},"announce":[],"urlList":[]}}