{"title":"TeenageDeliquents - Kenna Kane","uid":6658828,"size":437953731,"categoryP":"porn","categoryS":"movie_clips","magnet":"?xt=urn:btih:5786e0f9cb867dac0de360df4c83bbff586d65b3&amp;dn=TeenageDeliquents+-+Kenna+Kane&amp;tr=udp%3A%2F%2Ftracker.openbittorrent.com%3A80&amp;tr=udp%3A%2F%2Fopen.demonii.com%3A1337&amp;tr=udp%3A%2F%2Ftracker.coppersurfer.tk%3A6969&amp;tr=udp%3A%2F%2Fexodus.desync.com%3A6969","seeders":0,"leechers":1,"uploader":"Rabiner","files":3,"time":1315430173,"description":"TeenageDeliquents - Kenna Kane wmv\n\n\n &lt;a href=&quot;\nhttp://www.imagesnake.com/img/13895/1.jpg&quot; rel=&quot;nofollow&quot; target=&quot;_NEW&quot;&gt;\nhttp://www.imagesnake.com/img/13895/1.jpg&lt;/a&gt; \n &lt;a href=&quot;\nhttp://www.imagesnake.com/img/13896/pic.jpg&quot; rel=&quot;nofollow&quot; target=&quot;_NEW&quot;&gt;\nhttp://www.imagesnake.com/img/13896/pic.jpg&lt;/a&gt; ","torrent":{"xt":"urn:btih:5786e0f9cb867dac0de360df4c83bbff586d65b3","amp;dn":"TeenageDeliquents+-+Kenna+Kane","amp;tr":["udp%3A%2F%2Ftracker.openbittorrent.com%3A80","udp%3A%2F%2Fopen.demonii.com%3A1337","udp%3A%2F%2Ftracker.coppersurfer.tk%3A6969","udp%3A%2F%2Fexodus.desync.com%3A6969"],"infoHash":"5786e0f9cb867dac0de360df4c83bbff586d65b3","infoHashBuffer":{"type":"Buffer","data":[87,134,224,249,203,134,125,172,13,227,96,223,76,131,187,255,88,109,101,179]},"announce":[],"urlList":[]}}