{"title":"Fickschnitzel 5","uid":6590041,"size":1036209955,"categoryP":"porn","categoryS":"movies","magnet":"?xt=urn:btih:5e6a07f75316db26e6c2b1e56fa0152f3d940631&amp;dn=Fickschnitzel+5&amp;tr=udp%3A%2F%2Ftracker.openbittorrent.com%3A80&amp;tr=udp%3A%2F%2Fopen.demonii.com%3A1337&amp;tr=udp%3A%2F%2Ftracker.coppersurfer.tk%3A6969&amp;tr=udp%3A%2F%2Fexodus.desync.com%3A6969","seeders":0,"leechers":0,"uploader":"stabiloboy","files":-1,"time":1312795014,"description":"Das Schnitzel was man nicht essen kann !!!!! Aber SpaÃƒ","torrent":{"xt":"urn:btih:5e6a07f75316db26e6c2b1e56fa0152f3d940631","amp;dn":"Fickschnitzel+5","amp;tr":["udp%3A%2F%2Ftracker.openbittorrent.com%3A80","udp%3A%2F%2Fopen.demonii.com%3A1337","udp%3A%2F%2Ftracker.coppersurfer.tk%3A6969","udp%3A%2F%2Fexodus.desync.com%3A6969"],"infoHash":"5e6a07f75316db26e6c2b1e56fa0152f3d940631","infoHashBuffer":{"type":"Buffer","data":[94,106,7,247,83,22,219,38,230,194,177,229,111,160,21,47,61,148,6,49]},"announce":[],"urlList":[]}}