{"title":"OL.Yo.Murder.Busty.Suit.Woman.Caught.Tight.Work.Vol.7.YRZ-010.Ja","uid":6598060,"size":2191842820,"categoryP":"porn","categoryS":"movies","magnet":"?xt=urn:btih:6b31f1bbac0f59216c62d56a224566501bc71b2d&amp;dn=OL.Yo.Murder.Busty.Suit.Woman.Caught.Tight.Work.Vol.7.YRZ-010.Ja&amp;tr=udp%3A%2F%2Ftracker.openbittorrent.com%3A80&amp;tr=udp%3A%2F%2Fopen.demonii.com%3A1337&amp;tr=udp%3A%2F%2Ftracker.coppersurfer.tk%3A6969&amp;tr=udp%3A%2F%2Fexodus.desync.com%3A6969","seeders":0,"leechers":1,"uploader":"Rabiner","files":5,"time":1313097943,"description":"OL Yo Murder Busty Suit Woman Caught Tight Work Vol 7 YRZ-010 Jav Censored DVDRip XviD-MotTto\n\n\n &lt;a href=&quot;\nhttp://www.imagefruit.com/img/8642/1.jpg&quot; rel=&quot;nofollow&quot; target=&quot;_NEW&quot;&gt;\nhttp://www.imagefruit.com/img/8642/1.jpg&lt;/a&gt; \n &lt;a href=&quot;\nhttp://www.imagefruit.com/img/8643/2.jpg&quot; rel=&quot;nofollow&quot; target=&quot;_NEW&quot;&gt;\nhttp://www.imagefruit.com/img/8643/2.jpg&lt;/a&gt; \n &lt;a href=&quot;\nhttp://www.imagefruit.com/img/8644/3.jpg&quot; rel=&quot;nofollow&quot; target=&quot;_NEW&quot;&gt;\nhttp://www.imagefruit.com/img/8644/3.jpg&lt;/a&gt;\n &lt;a href=&quot;\nhttp://www.imagefruit.com/img/8645/front.jpg&quot; rel=&quot;nofollow&quot; target=&quot;_NEW&quot;&gt;\nhttp://www.imagefruit.com/img/8645/front.jpg&lt;/a&gt;","torrent":{"xt":"urn:btih:6b31f1bbac0f59216c62d56a224566501bc71b2d","amp;dn":"OL.Yo.Murder.Busty.Suit.Woman.Caught.Tight.Work.Vol.7.YRZ-010.Ja","amp;tr":["udp%3A%2F%2Ftracker.openbittorrent.com%3A80","udp%3A%2F%2Fopen.demonii.com%3A1337","udp%3A%2F%2Ftracker.coppersurfer.tk%3A6969","udp%3A%2F%2Fexodus.desync.com%3A6969"],"infoHash":"6b31f1bbac0f59216c62d56a224566501bc71b2d","infoHashBuffer":{"type":"Buffer","data":[107,49,241,187,172,15,89,33,108,98,213,106,34,69,102,80,27,199,27,45]},"announce":[],"urlList":[]}}