{"title":"Super.Hybrid.2010.720p.BRRiP.XViD.AC3-FLAWL3SS","uid":6596723,"size":2844842810,"categoryP":"video","categoryS":"hd___movies","magnet":"?xt=urn:btih:936105e93ad013dbcf7dfc8353f8dcd3d9595473&amp;dn=Super.Hybrid.2010.720p.BRRiP.XViD.AC3-FLAWL3SS&amp;tr=udp%3A%2F%2Ftracker.openbittorrent.com%3A80&amp;tr=udp%3A%2F%2Fopen.demonii.com%3A1337&amp;tr=udp%3A%2F%2Ftracker.coppersurfer.tk%3A6969&amp;tr=udp%3A%2F%2Fexodus.desync.com%3A6969","seeders":0,"leechers":1,"uploader":"UltraTorrents","files":3,"time":1313052519,"description":"\nInfo, Poster and Trailer:\n             &lt;a href=&quot;\nhttp://sharepixon.net/movies/super-hybrid&quot; rel=&quot;nofollow&quot; target=&quot;_NEW&quot;&gt;\nhttp://sharepixon.net/movies/super-hybrid&lt;/a&gt;\n\n\t","torrent":{"xt":"urn:btih:936105e93ad013dbcf7dfc8353f8dcd3d9595473","amp;dn":"Super.Hybrid.2010.720p.BRRiP.XViD.AC3-FLAWL3SS","amp;tr":["udp%3A%2F%2Ftracker.openbittorrent.com%3A80","udp%3A%2F%2Fopen.demonii.com%3A1337","udp%3A%2F%2Ftracker.coppersurfer.tk%3A6969","udp%3A%2F%2Fexodus.desync.com%3A6969"],"infoHash":"936105e93ad013dbcf7dfc8353f8dcd3d9595473","infoHashBuffer":{"type":"Buffer","data":[147,97,5,233,58,208,19,219,207,125,252,131,83,248,220,211,217,89,84,115]},"announce":[],"urlList":[]}}