{"title":"Filth.To.Ashes.Flesh.To.Dust.2011.DVDRip.XviD-ViP3R","uid":7027048,"size":734393074,"categoryP":"video","categoryS":"movies","magnet":"?xt=urn:btih:a4e61bda9cc3b6d08e1d7a088ec0d29f2ef455b9&amp;dn=Filth.To.Ashes.Flesh.To.Dust.2011.DVDRip.XviD-ViP3R&amp;tr=udp%3A%2F%2Ftracker.openbittorrent.com%3A80&amp;tr=udp%3A%2F%2Fopen.demonii.com%3A1337&amp;tr=udp%3A%2F%2Ftracker.coppersurfer.tk%3A6969&amp;tr=udp%3A%2F%2Fexodus.desync.com%3A6969","seeders":0,"leechers":0,"uploader":"crazy-torrent","files":2,"time":1329056992,"description":" &lt;a href=&quot;http://www.scenespeeds.com/&quot; rel=&quot;nofollow&quot; target=&quot;_NEW&quot;&gt;http://www.scenespeeds.com/&lt;/a&gt;\n\nDescription\n\nFilth.To.Ashes.Flesh.To.Dust.2011.DVDRip.XviD-ViP3R\n\nTiTLE.........[ Filth to Ashes, Flesh to Dust\nAUDiO.........[ 48000Hz 128 kb/s\nLANGUAGE......[ English\nViDEO.........[ 1014 kbps XviD 23.976 FPS\nRESOLUTiON....[ 624 x 272\nASPECT RATiO..[ 2.25:1\nSUBS..........[ None\nFiLES.........[ 1\nSiZE..........[ 700 MB\nRUNTIME.......[ 1:25:52\nGENRE.........[ Horror\nRARS..........[ Never\n\nIMDB: http://www.imdb.com/title/tt1499302/\nIMDB Rating: 4.0/10 (21 Votes)\nDIRECTOR: Paul Morrell\nWRITER: Derrick Bishop\nCAST: Meredith Laine, Linda Bella, Allison Ochmanek\n\nPLOT:\nPurge: To put to death, eliminate what is undesirable. The serial\nkiller known as Purge lived and died by this code. But is he dead?\nDriving home from a road trip, ERIC and SHELLY take a back road to\navoid a traffic jam. They encounter the serial killer Purge. Eric\nsurvives but Shelly is murdered. A year later, a group of adventure\nseeking high school grads venture to purge's lair. Among them is\nEric's brother JUAN. Eric sets out to save his brother, and get\nrevenge on Purge. For the six teens, their imperfections will be\nthe deciding factor if Purge shows them mercy. But if everyone is\nimperfect, will any of them survive?\n         &lt;a href=&quot;\nhttp://www.scenespeeds.com/&quot; rel=&quot;nofollow&quot; target=&quot;_NEW&quot;&gt;\nhttp://www.scenespeeds.com/&lt;/a&gt;\t","torrent":{"xt":"urn:btih:a4e61bda9cc3b6d08e1d7a088ec0d29f2ef455b9","amp;dn":"Filth.To.Ashes.Flesh.To.Dust.2011.DVDRip.XviD-ViP3R","amp;tr":["udp%3A%2F%2Ftracker.openbittorrent.com%3A80","udp%3A%2F%2Fopen.demonii.com%3A1337","udp%3A%2F%2Ftracker.coppersurfer.tk%3A6969","udp%3A%2F%2Fexodus.desync.com%3A6969"],"infoHash":"a4e61bda9cc3b6d08e1d7a088ec0d29f2ef455b9","infoHashBuffer":{"type":"Buffer","data":[164,230,27,218,156,195,182,208,142,29,122,8,142,192,210,159,46,244,85,185]},"announce":[],"urlList":[]}}