{"title":"Hard.Time.S03E05.Cellphone.War.HDTV.XviD-MOMENTUM","uid":6586165,"size":375807980,"categoryP":"video","categoryS":"tv_shows","magnet":"?xt=urn:btih:b3fbe6517ec2a8f46a2a8ae352fc1834a0086f2b&amp;dn=Hard.Time.S03E05.Cellphone.War.HDTV.XviD-MOMENTUM&amp;tr=udp%3A%2F%2Ftracker.openbittorrent.com%3A80&amp;tr=udp%3A%2F%2Fopen.demonii.com%3A1337&amp;tr=udp%3A%2F%2Ftracker.coppersurfer.tk%3A6969&amp;tr=udp%3A%2F%2Fexodus.desync.com%3A6969","seeders":0,"leechers":1,"uploader":"TvTeam","files":5,"time":1312621371,"description":". \n  &lt;a href=&quot;\nhttp://www.torrentday.com/&quot; rel=&quot;nofollow&quot; target=&quot;_NEW&quot;&gt;\nhttp://www.torrentday.com/&lt;/a&gt;        :     The Hottest Private Tracker On The Net!!!\n\n\nTo Avoid Fakes, ALWAYS Check That The Torrent Was Added By: TvTeam.\n\n\n               www . TorrentDay . Com \n(((((((((((((= Enjoy No RAR releases =))))))))))))))))))))\n\n...................................NFO:....................................\n\n.Hard.Time.S03E05.Cellphone.War.HDTV.XviD-MOMENTUM\n\nLink.............: http://channel.nationalgeographic.com/series/hard-time/5080/Overview\nRelease Date.....: 2011-08-03\nFilesize.........: 349.0MB\nRuntime..........: 00:44:58\nVideo............: 931kbps XviD\nAudio............: 144kbps MP3 2ch\nFrame Size.......: 624x352\nFrame Rate.......: 23.976","torrent":{"xt":"urn:btih:b3fbe6517ec2a8f46a2a8ae352fc1834a0086f2b","amp;dn":"Hard.Time.S03E05.Cellphone.War.HDTV.XviD-MOMENTUM","amp;tr":["udp%3A%2F%2Ftracker.openbittorrent.com%3A80","udp%3A%2F%2Fopen.demonii.com%3A1337","udp%3A%2F%2Ftracker.coppersurfer.tk%3A6969","udp%3A%2F%2Fexodus.desync.com%3A6969"],"infoHash":"b3fbe6517ec2a8f46a2a8ae352fc1834a0086f2b","infoHashBuffer":{"type":"Buffer","data":[179,251,230,81,126,194,168,244,106,42,138,227,82,252,24,52,160,8,111,43]},"announce":[],"urlList":[]}}