{"title":"Follar hasta reventar [Porno][Spanish].avi","uid":6866697,"size":733235200,"categoryP":"porn","categoryS":"movies","magnet":"?xt=urn:btih:b7d7cafdf24b9f466ff2731aceece92cfde3d29a&amp;dn=Follar+hasta+reventar+%5BPorno%5D%5BSpanish%5D.avi&amp;tr=udp%3A%2F%2Ftracker.openbittorrent.com%3A80&amp;tr=udp%3A%2F%2Fopen.demonii.com%3A1337&amp;tr=udp%3A%2F%2Ftracker.coppersurfer.tk%3A6969&amp;tr=udp%3A%2F%2Fexodus.desync.com%3A6969","seeders":0,"leechers":1,"uploader":"traperoyo","files":-1,"time":1323127867,"description":"Descripcion: Estas chicas saben exactamente lo que quieren. Y no estÃƒÂ¡n para perder el tiempo esperando. Si tÃƒÂº tambiÃƒÂ©n sabes lo que estÃƒÂ¡s buscando, esta pelÃƒÂ­cula es para ti. Porno alemÃƒÂ¡n sin medias tintas para personas con las ideas claras.","torrent":{"xt":"urn:btih:b7d7cafdf24b9f466ff2731aceece92cfde3d29a","amp;dn":"Follar+hasta+reventar+%5BPorno%5D%5BSpanish%5D.avi","amp;tr":["udp%3A%2F%2Ftracker.openbittorrent.com%3A80","udp%3A%2F%2Fopen.demonii.com%3A1337","udp%3A%2F%2Ftracker.coppersurfer.tk%3A6969","udp%3A%2F%2Fexodus.desync.com%3A6969"],"infoHash":"b7d7cafdf24b9f466ff2731aceece92cfde3d29a","infoHashBuffer":{"type":"Buffer","data":[183,215,202,253,242,75,159,70,111,242,115,26,206,236,233,44,253,227,210,154]},"announce":[],"urlList":[]}}