{"title":"BabyGotBoobs - Jacky Joy (Door To Door Whore)","uid":6869766,"size":340825276,"categoryP":"porn","categoryS":"movies","magnet":"?xt=urn:btih:baa3afbcea423d0b9114e4125b7a0101669ec1ce&amp;dn=BabyGotBoobs+-+Jacky+Joy+%28Door+To+Door+Whore%29&amp;tr=udp%3A%2F%2Ftracker.openbittorrent.com%3A80&amp;tr=udp%3A%2F%2Fopen.demonii.com%3A1337&amp;tr=udp%3A%2F%2Ftracker.coppersurfer.tk%3A6969&amp;tr=udp%3A%2F%2Fexodus.desync.com%3A6969","seeders":0,"leechers":0,"uploader":"kelvin09","files":1,"time":1323245116,"description":"BabyGotBoobs - Jacky Joy (Door To Door Whore)\n\n &lt;a href=&quot;\nhttp://www.seedimage.com/I/viewer.php?file=83213897784557042224.jpg&quot; rel=&quot;nofollow&quot; target=&quot;_NEW&quot;&gt;\nhttp://www.seedimage.com/I/viewer.php?file=83213897784557042224.jpg&lt;/a&gt;\n\n &lt;a href=&quot;\nhttp://www.seedimage.com/I/viewer.php?file=30335900950397984356.jpg&quot; rel=&quot;nofollow&quot; target=&quot;_NEW&quot;&gt;\nhttp://www.seedimage.com/I/viewer.php?file=30335900950397984356.jpg&lt;/a&gt;\n\n\nJacky Joy is down and out on her luck. The only pennies she has left are the two pretty little ones resting on each of her plump and round bazookas. Seeing that her plan of action is just not cutting it, she decides to take a different approach, utilizing her assets and pushing herself onto vulnerable and horny suburban men. End result: Two splendidly soaked tits showered down on by a rainfall of cum!","torrent":{"xt":"urn:btih:baa3afbcea423d0b9114e4125b7a0101669ec1ce","amp;dn":"BabyGotBoobs+-+Jacky+Joy+%28Door+To+Door+Whore%29","amp;tr":["udp%3A%2F%2Ftracker.openbittorrent.com%3A80","udp%3A%2F%2Fopen.demonii.com%3A1337","udp%3A%2F%2Ftracker.coppersurfer.tk%3A6969","udp%3A%2F%2Fexodus.desync.com%3A6969"],"infoHash":"baa3afbcea423d0b9114e4125b7a0101669ec1ce","infoHashBuffer":{"type":"Buffer","data":[186,163,175,188,234,66,61,11,145,20,228,18,91,122,1,1,102,158,193,206]},"announce":[],"urlList":[]}}