{"title":"Scent of woman e11","uid":6638342,"size":734670848,"categoryP":"video","categoryS":"tv_shows","magnet":"?xt=urn:btih:bae7a3590608cb6958a553c04b16a7f485d4b453&amp;dn=Scent+of+woman+e11&amp;tr=udp%3A%2F%2Ftracker.openbittorrent.com%3A80&amp;tr=udp%3A%2F%2Fopen.demonii.com%3A1337&amp;tr=udp%3A%2F%2Ftracker.coppersurfer.tk%3A6969&amp;tr=udp%3A%2F%2Fexodus.desync.com%3A6969","seeders":0,"leechers":1,"uploader":null,"files":1,"time":1314648586,"description":"Scent of woman e11","torrent":{"xt":"urn:btih:bae7a3590608cb6958a553c04b16a7f485d4b453","amp;dn":"Scent+of+woman+e11","amp;tr":["udp%3A%2F%2Ftracker.openbittorrent.com%3A80","udp%3A%2F%2Fopen.demonii.com%3A1337","udp%3A%2F%2Ftracker.coppersurfer.tk%3A6969","udp%3A%2F%2Fexodus.desync.com%3A6969"],"infoHash":"bae7a3590608cb6958a553c04b16a7f485d4b453","infoHashBuffer":{"type":"Buffer","data":[186,231,163,89,6,8,203,105,88,165,83,192,75,22,167,244,133,212,180,83]},"announce":[],"urlList":[]}}