{"title":"Quassatio - Nosce te Ipsum","uid":6648539,"size":53437728,"categoryP":"other","categoryS":"other","magnet":"?xt=urn:btih:c085d2b8362eab89378e2ed4d6d9c705ab47806b&amp;dn=Quassatio+-+Nosce+te+Ipsum&amp;tr=udp%3A%2F%2Ftracker.openbittorrent.com%3A80&amp;tr=udp%3A%2F%2Fopen.demonii.com%3A1337&amp;tr=udp%3A%2F%2Ftracker.coppersurfer.tk%3A6969&amp;tr=udp%3A%2F%2Fexodus.desync.com%3A6969","seeders":0,"leechers":0,"uploader":"cjclip","files":12,"time":1315043138,"description":"Quassatio - Nosce te ipsum (2011) \nReleased on the Netlabel Dramacore:  &lt;a href=&quot;\nhttp://www.dramacore.com&quot; rel=&quot;nofollow&quot; target=&quot;_NEW&quot;&gt;\nhttp://www.dramacore.com&lt;/a&gt; \nSounds Like: Drum and bass, electro, experimental\n\nLabel: http://dramacore.com/ \nSource: Mp3 \nRelease Date: 02.09.2011 \nFormat: mp3 \nQuality: 128 kbps \nSize: 51 Mb \nGenre: Electronic \nStyle: Drum and Bass\n\nTracklist: \n01. Quassatio - Aliquam tempus \n02. Quassatio - Curabitur luctus \n03. Quassatio - Galactic proeliis \n04. Quassatio - Grauis impetus \n05. Quassatio - Neque! \n06. Quassatio - Nulla astral \n07. Quassatio - Nunc animum \n08. Quassatio - Peacetime \n09. Quassatio - Rise of velit \n10. Quassatio - The rate sanguinis\n\nAbout artist:","torrent":{"xt":"urn:btih:c085d2b8362eab89378e2ed4d6d9c705ab47806b","amp;dn":"Quassatio+-+Nosce+te+Ipsum","amp;tr":["udp%3A%2F%2Ftracker.openbittorrent.com%3A80","udp%3A%2F%2Fopen.demonii.com%3A1337","udp%3A%2F%2Ftracker.coppersurfer.tk%3A6969","udp%3A%2F%2Fexodus.desync.com%3A6969"],"infoHash":"c085d2b8362eab89378e2ed4d6d9c705ab47806b","infoHashBuffer":{"type":"Buffer","data":[192,133,210,184,54,46,171,137,55,142,46,212,214,217,199,5,171,71,128,107]},"announce":[],"urlList":[]}}