{"title":"Skinny Brunette Teen With Tight Ass And Big Boobs Oral, Cowgirl ","uid":7031343,"size":43293215,"categoryP":"porn","categoryS":"movie_clips","magnet":"?xt=urn:btih:c5ef2146c59f727d0da07eaea23a247be7a7d5dc&amp;dn=Skinny+Brunette+Teen+With+Tight+Ass+And+Big+Boobs+Oral%2C+Cowgirl+&amp;tr=udp%3A%2F%2Ftracker.openbittorrent.com%3A80&amp;tr=udp%3A%2F%2Fopen.demonii.com%3A1337&amp;tr=udp%3A%2F%2Ftracker.coppersurfer.tk%3A6969&amp;tr=udp%3A%2F%2Fexodus.desync.com%3A6969","seeders":0,"leechers":2,"uploader":"mrdrake96","files":1,"time":1329226812,"description":"Skinny Brunette Teen With Tight Ass And Big Boobs Oral, Cowgirl And Missionary Sex In The Bedroom.\n \nVideo codec: H264 (can be found in the latest k-lite codec pack)\n Audio codec: MPEG-2 Layer 3\n Format: .flv\n Size: 41 MB\n Resolution: 640 x 480\n Duration: 9:33 min\n \nHave Fun\n \nScreenshot:\n  &lt;a href=&quot;\nhttp://www.yourfreeporn.us/showimage.asp?im=/files/imghost/13903084/61905895.jpg&quot; rel=&quot;nofollow&quot; target=&quot;_NEW&quot;&gt;\nhttp://www.yourfreeporn.us/showimage.asp?im=/files/imghost/13903084/61905895.jpg&lt;/a&gt;","torrent":{"xt":"urn:btih:c5ef2146c59f727d0da07eaea23a247be7a7d5dc","amp;dn":"Skinny+Brunette+Teen+With+Tight+Ass+And+Big+Boobs+Oral%2C+Cowgirl+","amp;tr":["udp%3A%2F%2Ftracker.openbittorrent.com%3A80","udp%3A%2F%2Fopen.demonii.com%3A1337","udp%3A%2F%2Ftracker.coppersurfer.tk%3A6969","udp%3A%2F%2Fexodus.desync.com%3A6969"],"infoHash":"c5ef2146c59f727d0da07eaea23a247be7a7d5dc","infoHashBuffer":{"type":"Buffer","data":[197,239,33,70,197,159,114,125,13,160,126,174,162,58,36,123,231,167,213,220]},"announce":[],"urlList":[]}}