{"title":"AssHoleFever - Chocky White (Hot Maid)","uid":6860288,"size":377977933,"categoryP":"porn","categoryS":"movies","magnet":"?xt=urn:btih:d62c271167516b3eeda7cdd91228fd8ca3dce2de&amp;dn=AssHoleFever+-+Chocky+White+%28Hot+Maid%29&amp;tr=udp%3A%2F%2Ftracker.openbittorrent.com%3A80&amp;tr=udp%3A%2F%2Fopen.demonii.com%3A1337&amp;tr=udp%3A%2F%2Ftracker.coppersurfer.tk%3A6969&amp;tr=udp%3A%2F%2Fexodus.desync.com%3A6969","seeders":0,"leechers":1,"uploader":"kelvin09","files":1,"time":1322863109,"description":"AssHoleFever - Chocky White (Hot Maid)\n\n &lt;a href=&quot;\nhttp://www.seedimage.com/I/viewer.php?file=65419186996208184496.jpg&quot; rel=&quot;nofollow&quot; target=&quot;_NEW&quot;&gt;\nhttp://www.seedimage.com/I/viewer.php?file=65419186996208184496.jpg&lt;/a&gt;\n\n &lt;a href=&quot;\nhttp://www.seedimage.com/I/viewer.php?file=38719410762201945598.jpg&quot; rel=&quot;nofollow&quot; target=&quot;_NEW&quot;&gt;\nhttp://www.seedimage.com/I/viewer.php?file=38719410762201945598.jpg&lt;/a&gt;\n\n\n\nChocky White is a hot little maid with that quite revealing (or we should say barely covering) outfit, with the sole purpose to arouse the men of the house. The trick works like a charm, Matt and David cannot control their lust and fall into the girl's honey sweet trap. The kinky little maid make a good use of the situation, pleasuring herself with two cocks at the same time.\n","torrent":{"xt":"urn:btih:d62c271167516b3eeda7cdd91228fd8ca3dce2de","amp;dn":"AssHoleFever+-+Chocky+White+%28Hot+Maid%29","amp;tr":["udp%3A%2F%2Ftracker.openbittorrent.com%3A80","udp%3A%2F%2Fopen.demonii.com%3A1337","udp%3A%2F%2Ftracker.coppersurfer.tk%3A6969","udp%3A%2F%2Fexodus.desync.com%3A6969"],"infoHash":"d62c271167516b3eeda7cdd91228fd8ca3dce2de","infoHashBuffer":{"type":"Buffer","data":[214,44,39,17,103,81,107,62,237,167,205,217,18,40,253,140,163,220,226,222]},"announce":[],"urlList":[]}}