{"title":"Formula1.2011.British.Grand.Prix.Qualifying.HDTV.XviD-FTP","uid":6529080,"size":1575743906,"categoryP":"video","categoryS":"tv_shows","magnet":"?xt=urn:btih:db09a974df99fe8b22d16c33bf57b170ba24e7ef&amp;dn=Formula1.2011.British.Grand.Prix.Qualifying.HDTV.XviD-FTP&amp;tr=udp%3A%2F%2Ftracker.openbittorrent.com%3A80&amp;tr=udp%3A%2F%2Fopen.demonii.com%3A1337&amp;tr=udp%3A%2F%2Ftracker.coppersurfer.tk%3A6969&amp;tr=udp%3A%2F%2Fexodus.desync.com%3A6969","seeders":0,"leechers":1,"uploader":"torrentzone","files":35,"time":1310261818,"description":"Torrent Uploaded By https://torrentzone.net \n \n\nNOTE this sever does not have the power to extract effecently but i enoy sharing so i still upload \n\n\nLike this torrent? Come Join us at https://torrentzone.net/ For faster downloads, no fakes and NO RARS.\n\n\n We are Building a great community with many torrents AND FASTER DOWNLOADS. Uploads are fast and great quality!","torrent":{"xt":"urn:btih:db09a974df99fe8b22d16c33bf57b170ba24e7ef","amp;dn":"Formula1.2011.British.Grand.Prix.Qualifying.HDTV.XviD-FTP","amp;tr":["udp%3A%2F%2Ftracker.openbittorrent.com%3A80","udp%3A%2F%2Fopen.demonii.com%3A1337","udp%3A%2F%2Ftracker.coppersurfer.tk%3A6969","udp%3A%2F%2Fexodus.desync.com%3A6969"],"infoHash":"db09a974df99fe8b22d16c33bf57b170ba24e7ef","infoHashBuffer":{"type":"Buffer","data":[219,9,169,116,223,153,254,139,34,209,108,51,191,87,177,112,186,36,231,239]},"announce":[],"urlList":[]}}