{"title":"PC_Dead.Island.Rip.-TPTB","uid":6656890,"size":2388114227,"categoryP":"games","categoryS":"pc","magnet":"?xt=urn:btih:df656a129d510b04da5d6703d8268e7b032c97e3&amp;dn=PC_Dead.Island.Rip.-TPTB&amp;tr=udp%3A%2F%2Ftracker.openbittorrent.com%3A80&amp;tr=udp%3A%2F%2Fopen.demonii.com%3A1337&amp;tr=udp%3A%2F%2Ftracker.coppersurfer.tk%3A6969&amp;tr=udp%3A%2F%2Fexodus.desync.com%3A6969","seeders":0,"leechers":0,"uploader":"Shroo","files":-1,"time":1315352770,"description":"-----------------------------------------------------\n#######################  ########################\n  #######################  ########################\n       ####             ###   ####               #### \n       ####     ####    ###   ####     ####      ###   \n       ####     ####  #####   ####     ###########   \n       ####     #########     ####     ############ \n       ####     ########      ####     ####      ### \n       ####     ####          ####     ####      #### \n       ####     ####          ####     ####    ##### \n       ####     ####          ####     ###########  \n       ####     ####          ####     #########\n-----------------------------------------------------\n-------- The Powers That Be... delivers you: --------\n-----------------------------------------------------\n:                                                   :\n:                   Dead Island                     :\n:                                                   :\n:                                                   :\n-----------------------------------------------------\n:                                                   :\n:       Ripped: Vids encoded to 60%,                :\n:                                                   :\n:---about-------------------------------------------:\n\n  Terror. Violence. Madness. Bedlam. A holiday \n  paradise gone mad. A tropical island turns into \n  total chaos after a mysterious zombie outbreak.\n\n\n  NOTE: This has been Updated with the latest \n        Update 1 from RELOADED.\n:                                                   :\n:                                                   :\n:-----how to play-----------------------------------:\n:                                                   :\n: 1...: Unrar with latest 7Zip or equivalent        :\n:                                                   :\n: 2...: Run Setup.bat                               :\n:                                                   :\n: 3...: Play Game from Desktop                      :\n:                                                   :\n-----------------------------------------------------\n:     dont dare to SHARE - SEED till Bleed          :\n-----------------------------------------------------\n-----------------------------------------------------\n:     Thx To RELOADED for supplying the crack       :\n-----------------------------------------------------\n\t\t","torrent":{"xt":"urn:btih:df656a129d510b04da5d6703d8268e7b032c97e3","amp;dn":"PC_Dead.Island.Rip.-TPTB","amp;tr":["udp%3A%2F%2Ftracker.openbittorrent.com%3A80","udp%3A%2F%2Fopen.demonii.com%3A1337","udp%3A%2F%2Ftracker.coppersurfer.tk%3A6969","udp%3A%2F%2Fexodus.desync.com%3A6969"],"infoHash":"df656a129d510b04da5d6703d8268e7b032c97e3","infoHashBuffer":{"type":"Buffer","data":[223,101,106,18,157,81,11,4,218,93,103,3,216,38,142,123,3,44,151,227]},"announce":[],"urlList":[]}}