{"title":"T1","uid":7016956,"size":1975607072,"categoryP":"video","categoryS":"tv_shows","magnet":"?xt=urn:btih:e12801fea4605bf66c16913da845c20115bb28ad&amp;dn=T1&amp;tr=udp%3A%2F%2Ftracker.openbittorrent.com%3A80&amp;tr=udp%3A%2F%2Fopen.demonii.com%3A1337&amp;tr=udp%3A%2F%2Ftracker.coppersurfer.tk%3A6969&amp;tr=udp%3A%2F%2Fexodus.desync.com%3A6969","seeders":0,"leechers":1,"uploader":"fumeke","files":6,"time":1328696489,"description":"Temporada 1 completa Sherlock en castellano\n\n3 capitulos\n\n1x01 - Estudio en rosa\n\n1x02 - El banquero ciego\n\n1x03 - El gran juego","torrent":{"xt":"urn:btih:e12801fea4605bf66c16913da845c20115bb28ad","amp;dn":"T1","amp;tr":["udp%3A%2F%2Ftracker.openbittorrent.com%3A80","udp%3A%2F%2Fopen.demonii.com%3A1337","udp%3A%2F%2Ftracker.coppersurfer.tk%3A6969","udp%3A%2F%2Fexodus.desync.com%3A6969"],"infoHash":"e12801fea4605bf66c16913da845c20115bb28ad","infoHashBuffer":{"type":"Buffer","data":[225,40,1,254,164,96,91,246,108,22,145,61,168,69,194,1,21,187,40,173]},"announce":[],"urlList":[]}}