{"title":"Dharmatma (1975) DVD9*NTSC (Dustorrents)","uid":6649717,"size":5404985482,"categoryP":"video","categoryS":"movies_dvdr","magnet":"?xt=urn:btih:e6acedf63a730826da1e8dbf7db27ac938937ea9&amp;dn=Dharmatma+%281975%29+DVD9%2ANTSC+%28Dustorrents%29&amp;tr=udp%3A%2F%2Ftracker.openbittorrent.com%3A80&amp;tr=udp%3A%2F%2Fopen.demonii.com%3A1337&amp;tr=udp%3A%2F%2Ftracker.coppersurfer.tk%3A6969&amp;tr=udp%3A%2F%2Fexodus.desync.com%3A6969","seeders":0,"leechers":0,"uploader":null,"files":20,"time":1315087202,"description":"===========Visit DUSTorrents.com for more Exclusives==============\n\nVisit DusTorrents.com for more exclusives....\n\nDusTorrents.com a Complete FreeLeech Site!! Registrations are absolutely FREE!!\n\nRegister by visiting..... www.dustorrents.com\n &lt;a href=&quot;\nhttp://www.dustorrents.com/dvd5-and-dvd9-releases/2776.htm#post19660&quot; rel=&quot;nofollow&quot; target=&quot;_NEW&quot;&gt;\nhttp://www.dustorrents.com/dvd5-and-dvd9-releases/2776.htm#post19660&lt;/a&gt;\n========================================================\n[CENTER]\n\n[B][COLOR=&quot;#FF0000&quot;][FONT=Arial Black]Freeleech !!![/FONT][/COLOR][/B]\n\n[IMG]http://img89.imageshack.us/img89/3435/95037114.png[/IMG]\n\n[IMG]http://img827.imageshack.us/img827/3463/18470874.png[/IMG]\n\n[B][COLOR=&quot;black&quot;][CODE]\nSource---------------------------------- DVD9 @ Dus WareHouse (:\nRipper---------------------------------- Married Patel !!\nCodec----------------------------------- DVD9\nResolution------------------------------ 720 X 480 (4:3)\nSubtitles------------------------------- English\nContainer------------------------------- VoB\nFrame Rate------------------------------ 23.976 fps\nAudio----------------------------------- 448 Kbps AC3   \nRip Size-------------------------------- 5.03 GB\nRunTime--------------------------------- 2:40:13\nIMDb Link------------------------------- [url=&quot;http://www.imdb.com/title/tt0361505/&quot;]Dharmatma (1975)[/url]\nNote------------------------------------ [B][COLOR=&quot;blue&quot;]Rain Of DVD9 Start!! Team Dus, Enjoyz ;)[/COLOR][/B][/CODE][/COLOR][/B]\n\n[CENTER][IMG]http://img21.imageshack.us/img21/3431/5vh6rom324kkccccthg.gif[/IMG]\n\n[IMG]http://img148.imageshack.us/img148/4378/73256807.png[/IMG]\n\n[IMG]http://img684.imageshack.us/img684/9339/98544265.png[/IMG]\n\n[IMG]http://img845.imageshack.us/img845/2254/28930329.png[/IMG]\n\n[IMG]http://img43.imageshack.us/img43/4351/65350565.png[/IMG]\n\n[B][COLOR=&quot;#FF0000&quot;][FONT=Arial Black]Freeleech !!![/FONT][/COLOR][/B]\n\n[IMG]http://img810.imageshack.us/img810/1918/dus111.gif[/IMG][/CENTER]\n\n[/CENTER]\n===========Visit DUSTorrents.com for more Exclusives==============\n\nVisit DusTorrents.com for more exclusives....\n\nDusTorrents.com a Complete FreeLeech Site!! Registrations are absolutely FREE!!\n\nRegister by visiting..... www.dustorrents.com\n &lt;a href=&quot;\nhttp://www.dustorrents.com/dvd5-and-dvd9-releases/2776.htm#post19660&quot; rel=&quot;nofollow&quot; target=&quot;_NEW&quot;&gt;\nhttp://www.dustorrents.com/dvd5-and-dvd9-releases/2776.htm#post19660&lt;/a&gt;\n========================================================","torrent":{"xt":"urn:btih:e6acedf63a730826da1e8dbf7db27ac938937ea9","amp;dn":"Dharmatma+%281975%29+DVD9%2ANTSC+%28Dustorrents%29","amp;tr":["udp%3A%2F%2Ftracker.openbittorrent.com%3A80","udp%3A%2F%2Fopen.demonii.com%3A1337","udp%3A%2F%2Ftracker.coppersurfer.tk%3A6969","udp%3A%2F%2Fexodus.desync.com%3A6969"],"infoHash":"e6acedf63a730826da1e8dbf7db27ac938937ea9","infoHashBuffer":{"type":"Buffer","data":[230,172,237,246,58,115,8,38,218,30,141,191,125,178,122,201,56,147,126,169]},"announce":[],"urlList":[]}}