{"title":"Neighbours.S27E121-E125.WS.PDTV.XviD-FQM","uid":6510508,"size":734351826,"categoryP":"video","categoryS":"tv_shows","magnet":"?xt=urn:btih:e819733e26fef2e551dde01a812874e008faa83c&amp;dn=Neighbours.S27E121-E125.WS.PDTV.XviD-FQM&amp;tr=udp%3A%2F%2Ftracker.openbittorrent.com%3A80&amp;tr=udp%3A%2F%2Fopen.demonii.com%3A1337&amp;tr=udp%3A%2F%2Ftracker.coppersurfer.tk%3A6969&amp;tr=udp%3A%2F%2Fexodus.desync.com%3A6969","seeders":0,"leechers":1,"uploader":"torrentzone","files":51,"time":1309602023,"description":"Torrent Uploaded By https://torrentzone.net \n \n\nNOTE this sever does not have the power to extract effecently but i enoy sharing so i still upload \n\n\nLike this torrent? Come Join us at https://torrentzone.net/ For faster downloads, no fakes and NO RARS.\n\n\n We are Building a great community with many torrents AND FASTER DOWNLOADS. Uploads are fast and great quality!","torrent":{"xt":"urn:btih:e819733e26fef2e551dde01a812874e008faa83c","amp;dn":"Neighbours.S27E121-E125.WS.PDTV.XviD-FQM","amp;tr":["udp%3A%2F%2Ftracker.openbittorrent.com%3A80","udp%3A%2F%2Fopen.demonii.com%3A1337","udp%3A%2F%2Ftracker.coppersurfer.tk%3A6969","udp%3A%2F%2Fexodus.desync.com%3A6969"],"infoHash":"e819733e26fef2e551dde01a812874e008faa83c","infoHashBuffer":{"type":"Buffer","data":[232,25,115,62,38,254,242,229,81,221,224,26,129,40,116,224,8,250,168,60]},"announce":[],"urlList":[]}}