{"title":"Submarine.School.S01E04.WS.PDTV.XviD-FTP","uid":6504779,"size":368407908,"categoryP":"video","categoryS":"tv_shows","magnet":"?xt=urn:btih:ecf90c62568da31d5e1945c5aa2362f82acc32ba&amp;dn=Submarine.School.S01E04.WS.PDTV.XviD-FTP&amp;tr=udp%3A%2F%2Ftracker.openbittorrent.com%3A80&amp;tr=udp%3A%2F%2Fopen.demonii.com%3A1337&amp;tr=udp%3A%2F%2Ftracker.coppersurfer.tk%3A6969&amp;tr=udp%3A%2F%2Fexodus.desync.com%3A6969","seeders":0,"leechers":1,"uploader":"sceneline","files":29,"time":1309385274,"description":"- &lt;a href=&quot;\nhttp://www.Speed.cd&quot; rel=&quot;nofollow&quot; target=&quot;_NEW&quot;&gt;\nhttp://www.Speed.cd&lt;/a&gt;       &lt;a href=&quot;\nhttp://www.Speed.cd&quot; rel=&quot;nofollow&quot; target=&quot;_NEW&quot;&gt;\nhttp://www.Speed.cd&lt;/a&gt;       the fast  and The Hottest Private Tracker on the net\n\nPlease Seed back to make the speed Faster!!!\n\n      ...... nfo..........\n\n-\n:::::::::::::::::::::::::::::::::::::::::::::::::::::::::::::::::::::::::::\n:::                                                                     :::\n:::  FFFFFFFFFFFFFFFFFFFFFFTTTTTTTTTTTTTTTTTTTTTTTPPPPPPPPPPPPPPPPP     :::\n:::  F::::::::::::::::::::FT:::::::::::::::::::::TP::::::::::::::::P    :::\n:::  F::::::::::::::::::::FT:::::::::::::::::::::TP::::::PPPPPP:::::P   :::\n:::  FF::::::FFFFFFFFF::::FT:::::TT:::::::TT:::::TPP:::::P     P:::::P  :::\n:::    F:::::F       FFFFFFTTTTTT  T:::::T  TTTTTT  P::::P     P:::::P  :::\n:::    F:::::F                     T:::::T          P::::P     P:::::P  :::\n:::    F::::::FFFFFFFFFF           T:::::T          P::::PPPPPP:::::P   :::\n:::    F:::::::::::::::F           T:::::T          P:::::::::::::PP    :::\n:::    F:::::::::::::::F           T:::::T          P::::PPPPPPPPP      :::\n:::    F::::::FFFFFFFFFF           T:::::T          P::::P              :::\n:::    F:::::F                     T:::::T          P::::P              :::\n:::    F:::::F                     T:::::T          P::::P              :::\n:::  FF:::::::FF                 TT:::::::TT      PP::::::PP            :::\n:::  F::::::::FF                 T:::::::::T      P::::::::P            :::\n:::  F::::::::FF                 T:::::::::T      P::::::::P            :::\n:::  FFFFFFFFFFF                 TTTTTTTTTTT      PPPPPPPPPP            :::\n:::                                                                     :::\n:::::::::::::::::::::::::::::::::::::::::::::::::::::::::::::::::::::::::::\n:::Release Name: Submarine.School.S01E04.WS.PDTV.XviD-FTP\n:::::::::::::::::::::::::::::::::::::::::::::::::::::::::::::::::::::::::::\n:::Air Date          : 29 June 2011 \n:::FTP Release Date  : 29 June 2011\n:::Video Format      : PDTV\n:::Video Resolution  : 624 X 352\n:::Audio Stream      : 128kbs ish VBR MP3\n:::Release Size      : 25 Files 350MB\n:::Genre             : Documentary\n:::Broardcast Channel: CHANNEL Five\n:::::::::::::::::::::::::::::::::::::::::::::::::::::::::::::::::::::::::::\nDescription: \nThe students face their toughest tests yet in their bid to \npass the Perisher course and become qualified to \ncommand their own nuclear submarines. But with a high \nfailure rate, the chances are that at least one of them will \nfall at this final hurdle. First they face all-out war in the \nclimax of the Nato Joint Warrior exercise, with two of the \nyoung officers forced to make tough decisions. Then just \none more exercise - with VIP top brass looking over their \nshoulders - before teacher Jim Perks makes his final \ndecision and reveals who has passed and who has \nfailed. \nURL Link : http://www.tvrage.com/shows/id-28632\n:::::::::::::::::::::::::::::::::::::::::::::::::::::::::::::::::::::::::::\n:::                             Other Notes                             :::\n:::                             -----------                             :::\n:::                                                                     :::\n:::                                                                     :::\n:::                                                                     :::\n:::::::::::::::::::::::::::::::::::::::::::::::::::::::::::::::::::::::::::\n:::                             Group Notes                             :::\n:::                             -----------                             :::\n:::                                                                     :::\n:::             We are not currenty looking for any new sites           :::\n:::                                                                     :::\n:::                                                                     :::\n:::                               Greets                                :::\n:::                               ------                                :::\n:::                                                                     :::\n:::                                                                     :::\n:::               (All The Uk Groups That Do There Share)               :::\n:::::::::::::::::::::::::::::::::::::::::::::::::::::::::::::::::::::::::::\n\nNFO Creator v.1 Coded by Us","torrent":{"xt":"urn:btih:ecf90c62568da31d5e1945c5aa2362f82acc32ba","amp;dn":"Submarine.School.S01E04.WS.PDTV.XviD-FTP","amp;tr":["udp%3A%2F%2Ftracker.openbittorrent.com%3A80","udp%3A%2F%2Fopen.demonii.com%3A1337","udp%3A%2F%2Ftracker.coppersurfer.tk%3A6969","udp%3A%2F%2Fexodus.desync.com%3A6969"],"infoHash":"ecf90c62568da31d5e1945c5aa2362f82acc32ba","infoHashBuffer":{"type":"Buffer","data":[236,249,12,98,86,141,163,29,94,25,69,197,170,35,98,248,42,204,50,186]},"announce":[],"urlList":[]}}