{"title":"[ECO-DvDRip]Kanchana-Muni2(2011)~500Mb~$TC Samurai$--TEAM TC--","uid":6586851,"size":525550220,"categoryP":"video","categoryS":"movies","magnet":"?xt=urn:btih:f19b66879d990f834813774ee179feba03625173&amp;dn=%5BECO-DvDRip%5DKanchana-Muni2%282011%29%7E500Mb%7E%24TC+Samurai%24--TEAM+TC--&amp;tr=udp%3A%2F%2Ftracker.openbittorrent.com%3A80&amp;tr=udp%3A%2F%2Fopen.demonii.com%3A1337&amp;tr=udp%3A%2F%2Ftracker.coppersurfer.tk%3A6969&amp;tr=udp%3A%2F%2Fexodus.desync.com%3A6969","seeders":0,"leechers":1,"uploader":"mohamedj","files":1,"time":1312642216,"description":"movie :Kanchana-Muni2...\n\nyear :2011\n\ncast : Raghava Lawrence,Lakshmi rai...\n\nsource: EconomyDVD\n\nfile format:Mp4\n\nsize:500Mb\n\nscreen resolution:720*320\n\ndisplay aspect ratio:2.250:1\n\nframe rate:23.976fps\n\nbit rate:434kbps\n\naudio bit rate:48.0Khz(2channels)\n\ncredits:TEAM TC\n\nSCREEN SHOTS:\n &lt;a href=&quot;\nhttp://imageshack.us/photo/my-images/717/vlcsnap2011080609h21m16.png/&quot; rel=&quot;nofollow&quot; target=&quot;_NEW&quot;&gt;\nhttp://imageshack.us/photo/my-images/717/vlcsnap2011080609h21m16.png/&lt;/a&gt;\n &lt;a href=&quot;\nhttp://imageshack.us/photo/my-images/7/vlcsnap2011080609h21m36.png/&quot; rel=&quot;nofollow&quot; target=&quot;_NEW&quot;&gt;\nhttp://imageshack.us/photo/my-images/7/vlcsnap2011080609h21m36.png/&lt;/a&gt;\n &lt;a href=&quot;\nhttp://imageshack.us/photo/my-images/52/vlcsnap2011080609h23m00.png/&quot; rel=&quot;nofollow&quot; target=&quot;_NEW&quot;&gt;\nhttp://imageshack.us/photo/my-images/52/vlcsnap2011080609h23m00.png/&lt;/a&gt;\n &lt;a href=&quot;\nhttp://imageshack.us/photo/my-images/135/vlcsnap2011080609h22m12.png/&quot; rel=&quot;nofollow&quot; target=&quot;_NEW&quot;&gt;\nhttp://imageshack.us/photo/my-images/135/vlcsnap2011080609h22m12.png/&lt;/a&gt;\n &lt;a href=&quot;\nhttp://imageshack.us/photo/my-images/580/vlcsnap2011080609h25m22.png/&quot; rel=&quot;nofollow&quot; target=&quot;_NEW&quot;&gt;\nhttp://imageshack.us/photo/my-images/580/vlcsnap2011080609h25m22.png/&lt;/a&gt;\n &lt;a href=&quot;\nhttp://imageshack.us/photo/my-images/685/vlcsnap2011080609h28m28.png/&quot; rel=&quot;nofollow&quot; target=&quot;_NEW&quot;&gt;\nhttp://imageshack.us/photo/my-images/685/vlcsnap2011080609h28m28.png/&lt;/a&gt;\n\n","torrent":{"xt":"urn:btih:f19b66879d990f834813774ee179feba03625173","amp;dn":"%5BECO-DvDRip%5DKanchana-Muni2%282011%29%7E500Mb%7E%24TC+Samurai%24--TEAM+TC--","amp;tr":["udp%3A%2F%2Ftracker.openbittorrent.com%3A80","udp%3A%2F%2Fopen.demonii.com%3A1337","udp%3A%2F%2Ftracker.coppersurfer.tk%3A6969","udp%3A%2F%2Fexodus.desync.com%3A6969"],"infoHash":"f19b66879d990f834813774ee179feba03625173","infoHashBuffer":{"type":"Buffer","data":[241,155,102,135,157,153,15,131,72,19,119,78,225,121,254,186,3,98,81,115]},"announce":[],"urlList":[]}}